MANIFEST.in
README
setup.py
plicata/__init__.py
plicata/manage.py
plicata/urls.py
plicata.egg-info/PKG-INFO
plicata.egg-info/SOURCES.txt
plicata.egg-info/dependency_links.txt
plicata.egg-info/requires.txt
plicata.egg-info/top_level.txt
plicata/authors/__init__.py
plicata/authors/admin.py
plicata/authors/db_router.py
plicata/authors/models.py
plicata/authors/tests.py
plicata/books/__init__.py
plicata/books/admin.py
plicata/books/models.py
plicata/books/page_processors.py
plicata/books/views.py
plicata/books/fixtures/genres.txt
plicata/characters/__init__.py
plicata/characters/admin.py
plicata/characters/models.py
plicata/characters/page_processors.py
plicata/characters/urls.py
plicata/characters/views.py
plicata/events/__init__.py
plicata/events/admin.py
plicata/events/models.py
plicata/events/page_processors.py
plicata/events/urls.py
plicata/events/views.py
plicata/plotlines/__init__.py
plicata/plotlines/models.py
plicata/reviews/__init__.py
plicata/reviews/admin.py
plicata/reviews/models.py
plicata/setting/__init__.py
plicata/setting/admin.py
plicata/setting/models.py
plicata/setting/page_processors.py
plicata/setting/urls.py
plicata/setting/views.py
plicata/templates/test.html