Metadata-Version: 1.0
Name: plicata
Version: 0.0.137
Summary: Django Application for Book Publishers
Home-page: http://plicata.com
Author: MiddleFork
Author-email: walker@mfgis.com
License: UNKNOWN
Platform: UNKNOWN
